anint/__init__.py
anint/config.py
anint/constants.py
anint/exceptions.py
anint/models.py
anint/py.typed
anint/setup.py
anint/translations.py
anint/utils.py
anint-0.3.2.dist-info/LICENSE
anint-0.3.2.dist-info/METADATA
anint-0.3.2.dist-info/WHEEL
anint-0.3.2.dist-info/top_level.txt
anint-0.3.2.dist-info/RECORD
